Metadata-Version: 2.1
Name: OpenFisca-Country-Template-draft
Version: 3.12.2
Summary: OpenFisca tax and benefit system for Country-Template
Home-page: https://github.com/openfisca/country-template
Author: OpenFisca Team
Author-email: contact@openfisca.org
License: http://www.fsf.org/licensing/licenses/agpl-3.0.html
Keywords: benefit microsimulation social tax
Platform: UNKNOWN
Classifier: Development Status :: 5 - Production/Stable
Classifier: License :: OSI Approved :: GNU Affero General Public License v3
Classifier: Operating System :: POSIX
Classifier: Programming Language :: Python
Classifier: Topic :: Scientific/Engineering :: Information Analysis
Requires-Dist: OpenFisca-Core[web-api] (<36.0,>=27.0)
Provides-Extra: dev
Requires-Dist: autopep8 (==1.5.4) ; extra == 'dev'
Requires-Dist: flake8 (<3.9.0,>=3.8.0) ; extra == 'dev'
Requires-Dist: flake8-import-order ; extra == 'dev'
Requires-Dist: flake8-print ; extra == 'dev'
Requires-Dist: pycodestyle (>=2.6.0) ; extra == 'dev'
